
{"items":[{"name":"Fp.Fs","href":"Fp.Fs.html","topicHref":"Fp.Fs.html","topicUid":"Fp.Fs","type":"Namespace","items":[{"name":"Coordinator","href":"Fp.Fs.Coordinator.html","topicHref":"Fp.Fs.Coordinator.html","topicUid":"Fp.Fs.Coordinator","type":"Class"},{"name":"Coordinator.ExecutionSettings","href":"Fp.Fs.Coordinator.ExecutionSettings.html","topicHref":"Fp.Fs.Coordinator.ExecutionSettings.html","topicUid":"Fp.Fs.Coordinator.ExecutionSettings","type":"Class"},{"name":"Coordinator.ExecutionSource","href":"Fp.Fs.Coordinator.ExecutionSource.html","topicHref":"Fp.Fs.Coordinator.ExecutionSource.html","topicUid":"Fp.Fs.Coordinator.ExecutionSource","type":"Class"},{"name":"Coordinator.FpInput","href":"Fp.Fs.Coordinator.FpInput.html","topicHref":"Fp.Fs.Coordinator.FpInput.html","topicUid":"Fp.Fs.Coordinator.FpInput","type":"Struct"},{"name":"Coordinator.FpTarget","href":"Fp.Fs.Coordinator.FpTarget.html","topicHref":"Fp.Fs.Coordinator.FpTarget.html","topicUid":"Fp.Fs.Coordinator.FpTarget","type":"Struct"},{"name":"DelegateFsProcessorFactory","href":"Fp.Fs.DelegateFsProcessorFactory.html","topicHref":"Fp.Fs.DelegateFsProcessorFactory.html","topicUid":"Fp.Fs.DelegateFsProcessorFactory","type":"Class"},{"name":"FileSystemSource","href":"Fp.Fs.FileSystemSource.html","topicHref":"Fp.Fs.FileSystemSource.html","topicUid":"Fp.Fs.FileSystemSource","type":"Class"},{"name":"FormatMultiProcessorFsWrapper","href":"Fp.Fs.FormatMultiProcessorFsWrapper.html","topicHref":"Fp.Fs.FormatMultiProcessorFsWrapper.html","topicUid":"Fp.Fs.FormatMultiProcessorFsWrapper","type":"Class"},{"name":"FormatMultiProcessorFsWrapper<T>","href":"Fp.Fs.FormatMultiProcessorFsWrapper-1.html","topicHref":"Fp.Fs.FormatMultiProcessorFsWrapper-1.html","topicUid":"Fp.Fs.FormatMultiProcessorFsWrapper`1","type":"Class"},{"name":"FormatSingleProcessorFsWrapper","href":"Fp.Fs.FormatSingleProcessorFsWrapper.html","topicHref":"Fp.Fs.FormatSingleProcessorFsWrapper.html","topicUid":"Fp.Fs.FormatSingleProcessorFsWrapper","type":"Class"},{"name":"FormatSingleProcessorFsWrapper<T>","href":"Fp.Fs.FormatSingleProcessorFsWrapper-1.html","topicHref":"Fp.Fs.FormatSingleProcessorFsWrapper-1.html","topicUid":"Fp.Fs.FormatSingleProcessorFsWrapper`1","type":"Class"},{"name":"FsFormatMultiProcessor","href":"Fp.Fs.FsFormatMultiProcessor.html","topicHref":"Fp.Fs.FsFormatMultiProcessor.html","topicUid":"Fp.Fs.FsFormatMultiProcessor","type":"Class"},{"name":"FsFormatSingleProcessor","href":"Fp.Fs.FsFormatSingleProcessor.html","topicHref":"Fp.Fs.FsFormatSingleProcessor.html","topicUid":"Fp.Fs.FsFormatSingleProcessor","type":"Class"},{"name":"FsFormatSingleProcessor<T>","href":"Fp.Fs.FsFormatSingleProcessor-1.html","topicHref":"Fp.Fs.FsFormatSingleProcessor-1.html","topicUid":"Fp.Fs.FsFormatSingleProcessor`1","type":"Class"},{"name":"FsProcessor","href":"Fp.Fs.FsProcessor.html","topicHref":"Fp.Fs.FsProcessor.html","topicUid":"Fp.Fs.FsProcessor","type":"Class"},{"name":"FsProcessorFactory","href":"Fp.Fs.FsProcessorFactory.html","topicHref":"Fp.Fs.FsProcessorFactory.html","topicUid":"Fp.Fs.FsProcessorFactory","type":"Class"},{"name":"FsProcessorInfoAttribute","href":"Fp.Fs.FsProcessorInfoAttribute.html","topicHref":"Fp.Fs.FsProcessorInfoAttribute.html","topicUid":"Fp.Fs.FsProcessorInfoAttribute","type":"Class"},{"name":"FsProcessorSource","href":"Fp.Fs.FsProcessorSource.html","topicHref":"Fp.Fs.FsProcessorSource.html","topicUid":"Fp.Fs.FsProcessorSource","type":"Class"},{"name":"GenericNewFsProcessorFactory<T>","href":"Fp.Fs.GenericNewFsProcessorFactory-1.html","topicHref":"Fp.Fs.GenericNewFsProcessorFactory-1.html","topicUid":"Fp.Fs.GenericNewFsProcessorFactory`1","type":"Class"},{"name":"RealFileSystemSource","href":"Fp.Fs.RealFileSystemSource.html","topicHref":"Fp.Fs.RealFileSystemSource.html","topicUid":"Fp.Fs.RealFileSystemSource","type":"Class"}]}],"memberLayout":"SamePage"}
